rtest-1.2.0.dist-info/METADATA
rtest-1.2.0.dist-info/WHEEL
rtest-1.2.0.dist-info/entry_points.txt
rtest-1.2.0.dist-info/licenses/LICENSE
rtest/__init__.py
rtest/_rtest.pyi
rtest/_rtest.pypy310-pp73-x86_64-linux-gnu.so
rtest/py.typed
rtest-1.2.0.dist-info/RECORD
