Metadata-Version: 2.4
Name: rtest
Version: 1.2.0
Classifier: Development Status :: 3 - Alpha
Classifier: Intended Audience :: Developers
Classifier: License :: OSI Approved :: MIT License
Classifier: Programming Language :: Python :: 3
Classifier: Programming Language :: Python :: 3.9
Classifier: Programming Language :: Python :: 3.10
Classifier: Programming Language :: Python :: 3.11
Classifier: Programming Language :: Python :: 3.12
Classifier: Programming Language :: Rust
Classifier: Topic :: Software Development :: Testing
Requires-Dist: pytest>=6.0
Requires-Dist: ruff==0.12.1 ; extra == 'dev'
Requires-Dist: mypy==1.16.1 ; extra == 'dev'
Provides-Extra: dev
License-File: LICENSE
Summary: A fast Python test runner built with Rust
Keywords: testing,pytest,rust,performance
Author-email: Hugh Han <hughhan1@gmail.com>
License: MIT
Requires-Python: >=3.9
